{
  "date": "20260130",
  "timestamp": "2026-01-30T00:00:00.000817+08:00",
  "prices": {
    "BTC-USDT-SWAP": 89447.8,
    "ETH-USDT-SWAP": 3006.4,
    "XRP-USDT-SWAP": 1.9067,
    "BNB-USDT-SWAP": 863.2,
    "SOL-USDT-SWAP": 117.59,
    "LTC-USDT-SWAP": 68.97,
    "DOGE-USDT-SWAP": 0.11612,
    "SUI-USDT-SWAP": 1.4031,
    "TRX-USDT-SWAP": 0.29095,
    "TON-USDT-SWAP": 1.518,
    "ETC-USDT-SWAP": 11.46,
    "BCH-USDT-SWAP": 552.3,
    "HBAR-USDT-SWAP": 0.10669,
    "XLM-USDT-SWAP": 0.19745,
    "FIL-USDT-SWAP": 1.261,
    "LINK-USDT-SWAP": 11.023,
    "CRO-USDT-SWAP": 0.09069,
    "DOT-USDT-SWAP": 1.845,
    "AAVE-USDT-SWAP": 160.35,
    "UNI-USDT-SWAP": 4.813,
    "NEAR-USDT-SWAP": 1.373,
    "APT-USDT-SWAP": 1.486,
    "CFX-USDT-SWAP": 0.0674,
    "CRV-USDT-SWAP": 0.3475,
    "STX-USDT-SWAP": 0.298,
    "LDO-USDT-SWAP": 0.5178,
    "TAO-USDT-SWAP": 238.4
  },
  "note": "\u65e5\u7ebf\u5f00\u76d8\u4ef7\uff08\u5f53\u59290\u70b9\u57fa\u51c6\u4ef7\uff09"
}